[
  {
    "eName": "English Name",
    "cName": "Chinese Name",
    "email": "email",
    "phone": "phone",
    "qq": "qq",
    "department": "department",
    "leader": "leader",
    "team": "project team",
    "position": "position",
    "hireDate": "hireDate",
    "hireStatus": "Active",
    "toStatus": "Active",
    "holidays": [
      {
        "type": "annual",
        "remain": "remain",
        "standard": "standard",
        "rest": "rest"
      },
      {
        "type": "overtime",
        "remain": "remain",
        "standard": "standard",
        "rest": "rest"
      },
      {
        "type": "affair",
        "remain": "remain",
        "standard": "standard",
        "rest": "rest"
      },
      {
        "type": "sick",
        "remain": "remain",
        "standard": "standard",
        "rest": "rest"
      },
      {
        "type": "marriage",
        "remain": "remain",
        "standard": "standard",
        "rest": "rest"
      },
      {
        "type": "maternity",
        "remain": "remain",
        "standard": "standard",
        "rest": "rest"
      },
      {
        "type": "funeral",
        "remain": "remain",
        "standard": "standard",
        "rest": "rest"
      }
    ]

  },
  {
    "eName": "English Name 1",
    "cName": "Chinese Name 1",
    "email": "email 1",
    "phone": "phone 1",
    "qq": "qq",
    "department": "department",
    "leader": "leader",
    "team": "project team",
    "position": "position",
    "hireDate": "hireDate",
    "hireStatus": "Active",
    "toStatus": "Active",
    "holidays": [
      {
        "type": "annual 1",
        "remain": "remain 1",
        "standard": "standard 1",
        "rest": "rest 1"
      },
      {
        "type": "overtime",
        "remain": "remain",
        "standard": "standard",
        "rest": "rest"
      },
      {
        "type": "affair",
        "remain": "remain",
        "standard": "standard",
        "rest": "rest"
      },
      {
        "type": "sick",
        "remain": "remain",
        "standard": "standard",
        "rest": "rest"
      },
      {
        "type": "marriage",
        "remain": "remain",
        "standard": "standard",
        "rest": "rest"
      },
      {
        "type": "maternity",
        "remain": "remain",
        "standard": "standard",
        "rest": "rest"
      },
      {
        "type": "funeral",
        "remain": "remain",
        "standard": "standard",
        "rest": "rest"
      }
    ]

  }
]